warrant/__init__.py
warrant/api_resource.py
warrant/authz.py
warrant/constants.py
warrant/feature.py
warrant/list_result.py
warrant/object.py
warrant/permission.py
warrant/pricing_tier.py
warrant/query_result.py
warrant/role.py
warrant/tenant.py
warrant/user.py
warrant/warrant.py
warrant_python-3.1.0.dist-info/LICENSE
warrant_python-3.1.0.dist-info/METADATA
warrant_python-3.1.0.dist-info/WHEEL
warrant_python-3.1.0.dist-info/top_level.txt
warrant_python-3.1.0.dist-info/RECORD
