Metadata-Version: 2.1
Name: warrant-python
Version: 3.1.0
Summary: Python SDK for Warrant
Home-page: https://github.com/warrant-dev/warrant-python
Author: Warrant
Author-email: hello@warrant.dev
License: Apache Software License (http://www.apache.org/licenses/LICENSE-2.0.txt)
Project-URL: Bug Tracker, https://github.com/warrant-dev/warrant-python/issues
Project-URL: Documentation, https://docs.warrant.dev
Project-URL: Source Code, https://github.com/warrant-dev/warrant-python
Keywords: warrant api authorization access control
Classifier: Intended Audience :: Developers
Classifier: Operating System :: OS Independent
Classifier: Programming Language :: Python
Classifier: Programming Language :: Python :: 3
Classifier: Programming Language :: Python :: 3.4
Classifier: Programming Language :: Python :: 3.5
Classifier: Programming Language :: Python :: 3.6
Classifier: Programming Language :: Python :: 3.7
Classifier: Programming Language :: Python :: 3.8
Classifier: Programming Language :: Python :: 3.9
Classifier: Topic :: Software Development :: Libraries :: Python Modules
License-File: LICENSE
Requires-Dist: requests
